actorcore/Actor.py
actorcore/CmdrConnection.py
actorcore/Command.py
actorcore/CommandLink.py
actorcore/CommandLinkManager.py
actorcore/ICC.py
actorcore/ICCExceptions.py
actorcore/TestHelper.py
actorcore/__init__.py
actorcore/help.py
actorcore/Commands/CoreCmd.py
actorcore/Commands/__init__.py
actorcore/utility/__init__.py
actorcore/utility/configuration.py
actorcore/utility/fits.py
sdss_actorcore-5.0.5.data/scripts/stageManager
stagemanager/__init__.py
stagemanager/stagemanager.py
stagemanager/etc/stageManager.cfg
sdss_actorcore-5.0.5.dist-info/LICENSE.md
sdss_actorcore-5.0.5.dist-info/METADATA
sdss_actorcore-5.0.5.dist-info/WHEEL
sdss_actorcore-5.0.5.dist-info/top_level.txt
sdss_actorcore-5.0.5.dist-info/RECORD
